CODE_OF_CONDUCT.md
LICENSE
MANIFEST.in
README.md
setup.cfg
setup.py
versioneer.py
elementable/__init__.py
elementable/_version.py
elementable/elementable.py
elementable/exceptions.py
elementable.egg-info/PKG-INFO
elementable.egg-info/SOURCES.txt
elementable.egg-info/dependency_links.txt
elementable.egg-info/top_level.txt
elementable/data/README.md
elementable/data/elements.json
elementable/data/test.py
elementable/tests/__init__.py
elementable/tests/base.py
elementable/tests/datafiles.py
elementable/tests/test_elementable.py
elementable/tests/test_openff.py
elementable/tests/test_openmm.py
elementable/tests/test_pydantic.py
elementable/tests/test_unyt.py
elementable/tests/.hypothesis/examples/26593b5ab9cf12d3/cd6bd1dcfebeffe9
elementable/tests/.hypothesis/examples/463a13a8bfbb8845/bec021b4f368e306
elementable/tests/.hypothesis/examples/599646ba981169ff/cd6bd1dcfebeffe9
elementable/tests/.hypothesis/unicode_data/13.0.0/charmap.json.gz
elementable/tests/data/vegetal.json