Metadata-Version: 2.1
Name: elementable
Version: 0.3.0
Summary:  Yet another elements package
Home-page: UNKNOWN
Author: Lily Wang
Author-email: lily@minium.com.au
License: MIT
Platform: UNKNOWN
License-File: LICENSE
